{
  "parasha": "Chayei Sara",
  "cycle": "annual",
  "aliyaNum": 6,
  "label": "Aliya 6 — Gen 25:1–11",
  "audio": "/parasha/chayei-sara/audio/aliya6.mp3",
  "duration": 123.69,
  "verses": [
    {
      "ref": "25:1",
      "words": [
        {
          "text": "וַיֹּ֧סֶף",
          "noTeamim": "וַיֹּסֶף",
          "plain": "ויסף",
          "morph": "וַ/יֹּ֧סֶף",
          "translit": "vayosef",
          "start": 0.0,
          "end": 3.038,
          "phraseBreak": null
        },
        {
          "text": "אַבְרָהָ֛ם",
          "noTeamim": "אַבְרָהָם",
          "plain": "אברהם",
          "morph": "אַבְרָהָ֛ם",
          "translit": "avraham",
          "start": 3.038,
          "end": 4.464,
          "phraseBreak": null
        },
        {
          "text": "וַיִּקַּ֥ח",
          "noTeamim": "וַיִּקַּח",
          "plain": "ויקח",
          "morph": "וַ/יִּקַּ֥ח",
          "translit": "vayikach",
          "start": 4.464,
          "end": 5.228,
          "phraseBreak": null
        },
        {
          "text": "אִשָּׁ֖ה",
          "noTeamim": "אִשָּׁה",
          "plain": "אשה",
          "morph": "אִשָּׁ֖ה",
          "translit": "isha",
          "start": 5.228,
          "end": 5.807,
          "phraseBreak": null
        },
        {
          "text": "וּשְׁמָ֥הּ",
          "noTeamim": "וּשְׁמָהּ",
          "plain": "ושמה",
          "morph": "וּ/שְׁמָ֥/הּ",
          "translit": "ushmah",
          "start": 5.807,
          "end": 6.406,
          "phraseBreak": null
        },
        {
          "text": "קְטוּרָֽה׃",
          "noTeamim": "קְטוּרָה׃",
          "plain": "קטורה",
          "morph": "קְטוּרָֽה׃",
          "translit": "ketura",
          "start": 6.406,
          "end": 7.543,
          "phraseBreak": "sof-pasuq"
        }
      ]
    },
    {
      "ref": "25:2",
      "words": [
        {
          "text": "וַתֵּ֣לֶד",
          "noTeamim": "וַתֵּלֶד",
          "plain": "ותלד",
          "morph": "וַ/תֵּ֣לֶד",
          "translit": "vateled",
          "start": 7.543,
          "end": 8.783,
          "phraseBreak": null
        },
        {
          "text": "ל֗וֹ",
          "noTeamim": "לוֹ",
          "plain": "לו",
          "morph": "ל֗/וֹ",
          "translit": "lo",
          "start": 8.783,
          "end": 9.982,
          "phraseBreak": null
        },
        {
          "text": "אֶת־",
          "noTeamim": "אֶת־",
          "plain": "את",
          "morph": "אֶת־",
          "translit": "et",
          "start": 9.982,
          "end": 10.581,
          "phraseBreak": null
        },
        {
          "text": "זִמְרָן֙",
          "noTeamim": "זִמְרָן",
          "plain": "זמרן",
          "morph": "זִמְרָן֙",
          "translit": "zimran",
          "start": 10.581,
          "end": 11.16,
          "phraseBreak": null
        },
        {
          "text": "וְאֶת־",
          "noTeamim": "וְאֶת־",
          "plain": "ואת",
          "morph": "וְ/אֶת־",
          "translit": "veet",
          "start": 11.16,
          "end": 11.655,
          "phraseBreak": null
        },
        {
          "text": "יָקְשָׁ֔ן",
          "noTeamim": "יָקְשָׁן",
          "plain": "יקשן",
          "morph": "יָקְשָׁ֔ן",
          "translit": "yakshan",
          "start": 11.655,
          "end": 12.255,
          "phraseBreak": "zaqef"
        },
        {
          "text": "וְאֶת־",
          "noTeamim": "וְאֶת־",
          "plain": "ואת",
          "morph": "וְ/אֶת־",
          "translit": "veet",
          "start": 12.255,
          "end": 12.771,
          "phraseBreak": null
        },
        {
          "text": "מְדָ֖ן",
          "noTeamim": "מְדָן",
          "plain": "מדן",
          "morph": "מְדָ֖ן",
          "translit": "medan",
          "start": 12.771,
          "end": 13.309,
          "phraseBreak": null
        },
        {
          "text": "וְאֶת־",
          "noTeamim": "וְאֶת־",
          "plain": "ואת",
          "morph": "וְ/אֶת־",
          "translit": "veet",
          "start": 13.309,
          "end": 13.66,
          "phraseBreak": null
        },
        {
          "text": "מִדְיָ֑ן",
          "noTeamim": "מִדְיָן",
          "plain": "מדין",
          "morph": "מִדְיָ֑ן",
          "translit": "midyan",
          "start": 13.66,
          "end": 14.218,
          "phraseBreak": "etnahta"
        },
        {
          "text": "וְאֶת־",
          "noTeamim": "וְאֶת־",
          "plain": "ואת",
          "morph": "וְ/אֶת־",
          "translit": "veet",
          "start": 14.218,
          "end": 15.003,
          "phraseBreak": null
        },
        {
          "text": "יִשְׁבָּ֖ק",
          "noTeamim": "יִשְׁבָּק",
          "plain": "ישבק",
          "morph": "יִשְׁבָּ֖ק",
          "translit": "yishbak",
          "start": 15.003,
          "end": 15.52,
          "phraseBreak": null
        },
        {
          "text": "וְאֶת־",
          "noTeamim": "וְאֶת־",
          "plain": "ואת",
          "morph": "וְ/אֶת־",
          "translit": "veet",
          "start": 15.52,
          "end": 16.016,
          "phraseBreak": null
        },
        {
          "text": "שֽׁוּחַ׃",
          "noTeamim": "שׁוּחַ׃",
          "plain": "שוח",
          "morph": "שֽׁוּחַ׃",
          "translit": "shuach",
          "start": 16.016,
          "end": 16.781,
          "phraseBreak": "sof-pasuq"
        }
      ]
    },
    {
      "ref": "25:3",
      "words": [
        {
          "text": "וְיָקְשָׁ֣ן",
          "noTeamim": "וְיָקְשָׁן",
          "plain": "ויקשן",
          "morph": "וְ/יָקְשָׁ֣ן",
          "translit": "veyakshan",
          "start": 16.781,
          "end": 18.083,
          "phraseBreak": null
        },
        {
          "text": "יָלַ֔ד",
          "noTeamim": "יָלַד",
          "plain": "ילד",
          "morph": "יָלַ֔ד",
          "translit": "yalad",
          "start": 18.083,
          "end": 18.661,
          "phraseBreak": "zaqef"
        },
        {
          "text": "אֶת־",
          "noTeamim": "אֶת־",
          "plain": "את",
          "morph": "אֶת־",
          "translit": "et",
          "start": 18.661,
          "end": 19.322,
          "phraseBreak": null
        },
        {
          "text": "שְׁבָ֖א",
          "noTeamim": "שְׁבָא",
          "plain": "שבא",
          "morph": "שְׁבָ֖א",
          "translit": "sheva",
          "start": 19.322,
          "end": 19.798,
          "phraseBreak": null
        },
        {
          "text": "וְאֶת־",
          "noTeamim": "וְאֶת־",
          "plain": "ואת",
          "morph": "וְ/אֶת־",
          "translit": "veet",
          "start": 19.798,
          "end": 20.294,
          "phraseBreak": null
        },
        {
          "text": "דְּדָ֑ן",
          "noTeamim": "דְּדָן",
          "plain": "דדן",
          "morph": "דְּדָ֑ן",
          "translit": "dedan",
          "start": 20.294,
          "end": 20.728,
          "phraseBreak": "etnahta"
        },
        {
          "text": "וּבְנֵ֣י",
          "noTeamim": "וּבְנֵי",
          "plain": "ובני",
          "morph": "וּ/בְנֵ֣י",
          "translit": "uvneiy",
          "start": 20.728,
          "end": 21.554,
          "phraseBreak": null
        },
        {
          "text": "דְדָ֔ן",
          "noTeamim": "דְדָן",
          "plain": "דדן",
          "morph": "דְדָ֔ן",
          "translit": "dedan",
          "start": 21.554,
          "end": 23.146,
          "phraseBreak": "zaqef"
        },
        {
          "text": "הָי֛וּ",
          "noTeamim": "הָיוּ",
          "plain": "היו",
          "morph": "הָי֛וּ",
          "translit": "hayu",
          "start": 23.146,
          "end": 24.861,
          "phraseBreak": null
        },
        {
          "text": "אַשּׁוּרִ֥ם",
          "noTeamim": "אַשּׁוּרִם",
          "plain": "אשורם",
          "morph": "אַשּׁוּרִ֥ם",
          "translit": "ashurim",
          "start": 24.861,
          "end": 25.894,
          "phraseBreak": null
        },
        {
          "text": "וּלְטוּשִׁ֖ים",
          "noTeamim": "וּלְטוּשִׁים",
          "plain": "ולטושים",
          "morph": "וּ/לְטוּשִׁ֖ים",
          "translit": "ultushiym",
          "start": 25.894,
          "end": 26.824,
          "phraseBreak": null
        },
        {
          "text": "וּלְאֻמִּֽים׃",
          "noTeamim": "וּלְאֻמִּים׃",
          "plain": "ולאמים",
          "morph": "וּ/לְאֻמִּֽים׃",
          "translit": "ulumiym",
          "start": 26.824,
          "end": 28.043,
          "phraseBreak": "sof-pasuq"
        }
      ]
    },
    {
      "ref": "25:4",
      "words": [
        {
          "text": "וּבְנֵ֣י",
          "noTeamim": "וּבְנֵי",
          "plain": "ובני",
          "morph": "וּ/בְנֵ֣י",
          "translit": "uvneiy",
          "start": 28.043,
          "end": 29.614,
          "phraseBreak": null
        },
        {
          "text": "מִדְיָ֗ן",
          "noTeamim": "מִדְיָן",
          "plain": "מדין",
          "morph": "מִדְיָ֗ן",
          "translit": "midyan",
          "start": 29.614,
          "end": 30.999,
          "phraseBreak": null
        },
        {
          "text": "עֵיפָ֤ה",
          "noTeamim": "עֵיפָה",
          "plain": "עיפה",
          "morph": "עֵיפָ֤ה",
          "translit": "eiyfa",
          "start": 30.999,
          "end": 32.094,
          "phraseBreak": null
        },
        {
          "text": "וָעֵ֙פֶר֙",
          "noTeamim": "וָעֵפֶר",
          "plain": "ועפר",
          "morph": "וָ/עֵ֙פֶר֙",
          "translit": "vaefer",
          "start": 32.094,
          "end": 33.024,
          "phraseBreak": null
        },
        {
          "text": "וַחֲנֹ֔ךְ",
          "noTeamim": "וַחֲנֹךְ",
          "plain": "וחנך",
          "morph": "וַ/חֲנֹ֔ךְ",
          "translit": "vachanoch",
          "start": 33.024,
          "end": 33.809,
          "phraseBreak": "zaqef"
        },
        {
          "text": "וַאֲבִידָ֖ע",
          "noTeamim": "וַאֲבִידָע",
          "plain": "ואבידע",
          "morph": "וַ/אֲבִידָ֖ע",
          "translit": "vaaviyda",
          "start": 33.809,
          "end": 34.946,
          "phraseBreak": null
        },
        {
          "text": "וְאֶלְדָּעָ֑ה",
          "noTeamim": "וְאֶלְדָּעָה",
          "plain": "ואלדעה",
          "morph": "וְ/אֶלְדָּעָ֑ה",
          "translit": "veeldaa",
          "start": 34.946,
          "end": 35.855,
          "phraseBreak": "etnahta"
        },
        {
          "text": "כָּל־",
          "noTeamim": "כָּל־",
          "plain": "כל",
          "morph": "כָּל־",
          "translit": "kal",
          "start": 35.855,
          "end": 36.516,
          "phraseBreak": null
        },
        {
          "text": "אֵ֖לֶּה",
          "noTeamim": "אֵלֶּה",
          "plain": "אלה",
          "morph": "אֵ֖לֶּה",
          "translit": "ele",
          "start": 36.516,
          "end": 36.971,
          "phraseBreak": null
        },
        {
          "text": "בְּנֵ֥י",
          "noTeamim": "בְּנֵי",
          "plain": "בני",
          "morph": "בְּנֵ֥י",
          "translit": "beneiy",
          "start": 36.971,
          "end": 37.508,
          "phraseBreak": null
        },
        {
          "text": "קְטוּרָֽה׃",
          "noTeamim": "קְטוּרָה׃",
          "plain": "קטורה",
          "morph": "קְטוּרָֽה׃",
          "translit": "ketura",
          "start": 37.508,
          "end": 38.314,
          "phraseBreak": "sof-pasuq"
        }
      ]
    },
    {
      "ref": "25:5",
      "words": [
        {
          "text": "וַיִּתֵּ֧ן",
          "noTeamim": "וַיִּתֵּן",
          "plain": "ויתן",
          "morph": "וַ/יִּתֵּ֧ן",
          "translit": "vayiten",
          "start": 38.314,
          "end": 40.526,
          "phraseBreak": null
        },
        {
          "text": "אַבְרָהָ֛ם",
          "noTeamim": "אַבְרָהָם",
          "plain": "אברהם",
          "morph": "אַבְרָהָ֛ם",
          "translit": "avraham",
          "start": 40.526,
          "end": 41.848,
          "phraseBreak": null
        },
        {
          "text": "אֶת־",
          "noTeamim": "אֶת־",
          "plain": "את",
          "morph": "אֶת־",
          "translit": "et",
          "start": 41.848,
          "end": 42.261,
          "phraseBreak": null
        },
        {
          "text": "כָּל־",
          "noTeamim": "כָּל־",
          "plain": "כל",
          "morph": "כָּל־",
          "translit": "kal",
          "start": 42.261,
          "end": 42.571,
          "phraseBreak": null
        },
        {
          "text": "אֲשֶׁר־",
          "noTeamim": "אֲשֶׁר־",
          "plain": "אשר",
          "morph": "אֲשֶׁר־",
          "translit": "asher",
          "start": 42.571,
          "end": 42.923,
          "phraseBreak": null
        },
        {
          "text": "ל֖וֹ",
          "noTeamim": "לוֹ",
          "plain": "לו",
          "morph": "ל֖/וֹ",
          "translit": "lo",
          "start": 42.923,
          "end": 43.315,
          "phraseBreak": null
        },
        {
          "text": "לְיִצְחָֽק׃",
          "noTeamim": "לְיִצְחָק׃",
          "plain": "ליצחק",
          "morph": "לְ/יִצְחָֽק׃",
          "translit": "leyitzchak",
          "start": 43.315,
          "end": 44.287,
          "phraseBreak": "sof-pasuq"
        }
      ]
    },
    {
      "ref": "25:6",
      "words": [
        {
          "text": "וְלִבְנֵ֤י",
          "noTeamim": "וְלִבְנֵי",
          "plain": "ולבני",
          "morph": "וְ/לִ/בְנֵ֤י",
          "translit": "velivneiy",
          "start": 44.287,
          "end": 47.717,
          "phraseBreak": null
        },
        {
          "text": "הַפִּֽילַגְשִׁים֙",
          "noTeamim": "הַפִּילַגְשִׁים",
          "plain": "הפילגשים",
          "morph": "הַ/פִּֽילַגְשִׁים֙",
          "translit": "hapiylagshiym",
          "start": 47.717,
          "end": 48.751,
          "phraseBreak": null
        },
        {
          "text": "אֲשֶׁ֣ר",
          "noTeamim": "אֲשֶׁר",
          "plain": "אשר",
          "morph": "אֲשֶׁ֣ר",
          "translit": "asher",
          "start": 48.751,
          "end": 49.432,
          "phraseBreak": null
        },
        {
          "text": "לְאַבְרָהָ֔ם",
          "noTeamim": "לְאַבְרָהָם",
          "plain": "לאברהם",
          "morph": "לְ/אַבְרָהָ֔ם",
          "translit": "leavraham",
          "start": 49.432,
          "end": 50.342,
          "phraseBreak": "zaqef"
        },
        {
          "text": "נָתַ֥ן",
          "noTeamim": "נָתַן",
          "plain": "נתן",
          "morph": "נָתַ֥ן",
          "translit": "natan",
          "start": 50.342,
          "end": 51.933,
          "phraseBreak": null
        },
        {
          "text": "אַבְרָהָ֖ם",
          "noTeamim": "אַבְרָהָם",
          "plain": "אברהם",
          "morph": "אַבְרָהָ֖ם",
          "translit": "avraham",
          "start": 51.933,
          "end": 52.656,
          "phraseBreak": null
        },
        {
          "text": "מַתָּנֹ֑ת",
          "noTeamim": "מַתָּנֹת",
          "plain": "מתנת",
          "morph": "מַתָּנֹ֑ת",
          "translit": "matanot",
          "start": 52.656,
          "end": 53.421,
          "phraseBreak": "etnahta"
        },
        {
          "text": "וַֽיְשַׁלְּחֵ֞ם",
          "noTeamim": "וַיְשַׁלְּחֵם",
          "plain": "וישלחם",
          "morph": "וַֽ/יְשַׁלְּחֵ֞/ם",
          "translit": "vayshalchem",
          "start": 53.421,
          "end": 55.219,
          "phraseBreak": null
        },
        {
          "text": "מֵעַ֨ל",
          "noTeamim": "מֵעַל",
          "plain": "מעל",
          "morph": "מֵ/עַ֨ל",
          "translit": "meal",
          "start": 55.219,
          "end": 56.707,
          "phraseBreak": null
        },
        {
          "text": "יִצְחָ֤ק",
          "noTeamim": "יִצְחָק",
          "plain": "יצחק",
          "morph": "יִצְחָ֤ק",
          "translit": "yitzchak",
          "start": 56.707,
          "end": 57.285,
          "phraseBreak": null
        },
        {
          "text": "בְּנוֹ֙",
          "noTeamim": "בְּנוֹ",
          "plain": "בנו",
          "morph": "בְּנ/וֹ֙",
          "translit": "beno",
          "start": 57.285,
          "end": 57.719,
          "phraseBreak": null
        },
        {
          "text": "בְּעוֹדֶ֣נּוּ",
          "noTeamim": "בְּעוֹדֶנּוּ",
          "plain": "בעודנו",
          "morph": "בְּ/עוֹדֶ֣/נּוּ",
          "translit": "beodenu",
          "start": 57.719,
          "end": 58.691,
          "phraseBreak": null
        },
        {
          "text": "חַ֔י",
          "noTeamim": "חַי",
          "plain": "חי",
          "morph": "חַ֔י",
          "translit": "chay",
          "start": 58.691,
          "end": 59.042,
          "phraseBreak": "zaqef"
        },
        {
          "text": "קֵ֖דְמָה",
          "noTeamim": "קֵדְמָה",
          "plain": "קדמה",
          "morph": "קֵ֖דְמָ/ה",
          "translit": "kedma",
          "start": 59.042,
          "end": 60.055,
          "phraseBreak": null
        },
        {
          "text": "אֶל־",
          "noTeamim": "אֶל־",
          "plain": "אל",
          "morph": "אֶל־",
          "translit": "el",
          "start": 60.055,
          "end": 60.406,
          "phraseBreak": null
        },
        {
          "text": "אֶ֥רֶץ",
          "noTeamim": "אֶרֶץ",
          "plain": "ארץ",
          "morph": "אֶ֥רֶץ",
          "translit": "eretz",
          "start": 60.406,
          "end": 60.819,
          "phraseBreak": null
        },
        {
          "text": "קֶֽדֶם׃",
          "noTeamim": "קֶדֶם׃",
          "plain": "קדם",
          "morph": "קֶֽדֶם׃",
          "translit": "kedem",
          "start": 60.819,
          "end": 61.315,
          "phraseBreak": "sof-pasuq"
        }
      ]
    },
    {
      "ref": "25:7",
      "words": [
        {
          "text": "וְאֵ֗לֶּה",
          "noTeamim": "וְאֵלֶּה",
          "plain": "ואלה",
          "morph": "וְ/אֵ֗לֶּה",
          "translit": "veele",
          "start": 61.315,
          "end": 64.167,
          "phraseBreak": null
        },
        {
          "text": "יְמֵ֛י",
          "noTeamim": "יְמֵי",
          "plain": "ימי",
          "morph": "יְמֵ֛י",
          "translit": "yemeiy",
          "start": 64.167,
          "end": 65.572,
          "phraseBreak": null
        },
        {
          "text": "שְׁנֵֽי־",
          "noTeamim": "שְׁנֵי־",
          "plain": "שני",
          "morph": "שְׁנֵֽי־",
          "translit": "sheneiy",
          "start": 65.572,
          "end": 66.316,
          "phraseBreak": null
        },
        {
          "text": "חַיֵּ֥י",
          "noTeamim": "חַיֵּי",
          "plain": "חיי",
          "morph": "חַיֵּ֥י",
          "translit": "chayeiy",
          "start": 66.316,
          "end": 66.916,
          "phraseBreak": null
        },
        {
          "text": "אַבְרָהָ֖ם",
          "noTeamim": "אַבְרָהָם",
          "plain": "אברהם",
          "morph": "אַבְרָהָ֖ם",
          "translit": "avraham",
          "start": 66.916,
          "end": 67.37,
          "phraseBreak": null
        },
        {
          "text": "אֲשֶׁר־",
          "noTeamim": "אֲשֶׁר־",
          "plain": "אשר",
          "morph": "אֲשֶׁר־",
          "translit": "asher",
          "start": 67.37,
          "end": 67.66,
          "phraseBreak": null
        },
        {
          "text": "חָ֑י",
          "noTeamim": "חָי",
          "plain": "חי",
          "morph": "חָ֑י",
          "translit": "chay",
          "start": 67.66,
          "end": 68.135,
          "phraseBreak": "etnahta"
        },
        {
          "text": "מְאַ֥ת",
          "noTeamim": "מְאַת",
          "plain": "מאת",
          "morph": "מְאַ֥ת",
          "translit": "meat",
          "start": 68.135,
          "end": 69.334,
          "phraseBreak": null
        },
        {
          "text": "שָׁנָ֛ה",
          "noTeamim": "שָׁנָה",
          "plain": "שנה",
          "morph": "שָׁנָ֛ה",
          "translit": "shana",
          "start": 69.334,
          "end": 70.491,
          "phraseBreak": null
        },
        {
          "text": "וְשִׁבְעִ֥ים",
          "noTeamim": "וְשִׁבְעִים",
          "plain": "ושבעים",
          "morph": "וְ/שִׁבְעִ֥ים",
          "translit": "veshiviym",
          "start": 70.491,
          "end": 71.07,
          "phraseBreak": null
        },
        {
          "text": "שָׁנָ֖ה",
          "noTeamim": "שָׁנָה",
          "plain": "שנה",
          "morph": "שָׁנָ֖ה",
          "translit": "shana",
          "start": 71.07,
          "end": 71.566,
          "phraseBreak": null
        },
        {
          "text": "וְחָמֵ֥שׁ",
          "noTeamim": "וְחָמֵשׁ",
          "plain": "וחמש",
          "morph": "וְ/חָמֵ֥שׁ",
          "translit": "vechamesh",
          "start": 71.566,
          "end": 72.268,
          "phraseBreak": null
        },
        {
          "text": "שָׁנִֽים׃",
          "noTeamim": "שָׁנִים׃",
          "plain": "שנים",
          "morph": "שָׁנִֽים׃",
          "translit": "shaniym",
          "start": 72.268,
          "end": 72.929,
          "phraseBreak": "sof-pasuq"
        }
      ]
    },
    {
      "ref": "25:8",
      "words": [
        {
          "text": "וַיִּגְוַ֨ע",
          "noTeamim": "וַיִּגְוַע",
          "plain": "ויגוע",
          "morph": "וַ/יִּגְוַ֨ע",
          "translit": "vayigva",
          "start": 72.929,
          "end": 74.603,
          "phraseBreak": null
        },
        {
          "text": "וַיָּ֧מָת",
          "noTeamim": "וַיָּמָת",
          "plain": "וימת",
          "morph": "וַ/יָּ֧מָת",
          "translit": "vayamat",
          "start": 74.603,
          "end": 76.319,
          "phraseBreak": null
        },
        {
          "text": "אַבְרָהָ֛ם",
          "noTeamim": "אַבְרָהָם",
          "plain": "אברהם",
          "morph": "אַבְרָהָ֛ם",
          "translit": "avraham",
          "start": 76.319,
          "end": 77.538,
          "phraseBreak": null
        },
        {
          "text": "בְּשֵׂיבָ֥ה",
          "noTeamim": "בְּשֵׂיבָה",
          "plain": "בשיבה",
          "morph": "בְּ/שֵׂיבָ֥ה",
          "translit": "beseiyva",
          "start": 77.538,
          "end": 78.571,
          "phraseBreak": null
        },
        {
          "text": "טוֹבָ֖ה",
          "noTeamim": "טוֹבָה",
          "plain": "טובה",
          "morph": "טוֹבָ֖ה",
          "translit": "tova",
          "start": 78.571,
          "end": 79.047,
          "phraseBreak": null
        },
        {
          "text": "זָקֵ֣ן",
          "noTeamim": "זָקֵן",
          "plain": "זקן",
          "morph": "זָקֵ֣ן",
          "translit": "zaken",
          "start": 79.047,
          "end": 79.419,
          "phraseBreak": null
        },
        {
          "text": "וְשָׂבֵ֑עַ",
          "noTeamim": "וְשָׂבֵעַ",
          "plain": "ושבע",
          "morph": "וְ/שָׂבֵ֑עַ",
          "translit": "vesave'a",
          "start": 79.419,
          "end": 80.245,
          "phraseBreak": "etnahta"
        },
        {
          "text": "וַיֵּאָ֖סֶף",
          "noTeamim": "וַיֵּאָסֶף",
          "plain": "ויאסף",
          "morph": "וַ/יֵּאָ֖סֶף",
          "translit": "vayeasef",
          "start": 80.245,
          "end": 81.65,
          "phraseBreak": null
        },
        {
          "text": "אֶל־",
          "noTeamim": "אֶל־",
          "plain": "אל",
          "morph": "אֶל־",
          "translit": "el",
          "start": 81.65,
          "end": 82.146,
          "phraseBreak": null
        },
        {
          "text": "עַמָּֽיו׃",
          "noTeamim": "עַמָּיו׃",
          "plain": "עמיו",
          "morph": "עַמָּֽי/ו׃",
          "translit": "amayv",
          "start": 82.146,
          "end": 82.849,
          "phraseBreak": "sof-pasuq"
        }
      ]
    },
    {
      "ref": "25:9",
      "words": [
        {
          "text": "וַיִּקְבְּר֨וּ",
          "noTeamim": "וַיִּקְבְּרוּ",
          "plain": "ויקברו",
          "morph": "וַ/יִּקְבְּר֨וּ",
          "translit": "vayikbru",
          "start": 82.849,
          "end": 84.358,
          "phraseBreak": null
        },
        {
          "text": "אֹת֜וֹ",
          "noTeamim": "אֹתוֹ",
          "plain": "אתו",
          "morph": "אֹת֜/וֹ",
          "translit": "oto",
          "start": 84.358,
          "end": 85.618,
          "phraseBreak": null
        },
        {
          "text": "יִצְחָ֤ק",
          "noTeamim": "יִצְחָק",
          "plain": "יצחק",
          "morph": "יִצְחָ֤ק",
          "translit": "yitzchak",
          "start": 85.618,
          "end": 86.528,
          "phraseBreak": null
        },
        {
          "text": "וְיִשְׁמָעֵאל֙",
          "noTeamim": "וְיִשְׁמָעֵאל",
          "plain": "וישמעאל",
          "morph": "וְ/יִשְׁמָעֵאל֙",
          "translit": "veyishmael",
          "start": 86.528,
          "end": 87.375,
          "phraseBreak": null
        },
        {
          "text": "בָּנָ֔יו",
          "noTeamim": "בָּנָיו",
          "plain": "בניו",
          "morph": "בָּנָ֔י/ו",
          "translit": "banayv",
          "start": 87.375,
          "end": 88.16,
          "phraseBreak": "zaqef"
        },
        {
          "text": "אֶל־",
          "noTeamim": "אֶל־",
          "plain": "אל",
          "morph": "אֶל־",
          "translit": "el",
          "start": 88.16,
          "end": 88.511,
          "phraseBreak": null
        },
        {
          "text": "מְעָרַ֖ת",
          "noTeamim": "מְעָרַת",
          "plain": "מערת",
          "morph": "מְעָרַ֖ת",
          "translit": "mearat",
          "start": 88.511,
          "end": 89.09,
          "phraseBreak": null
        },
        {
          "text": "הַמַּכְפֵּלָ֑ה",
          "noTeamim": "הַמַּכְפֵּלָה",
          "plain": "המכפלה",
          "morph": "הַ/מַּכְפֵּלָ֑ה",
          "translit": "hamachpela",
          "start": 89.09,
          "end": 89.937,
          "phraseBreak": "etnahta"
        },
        {
          "text": "אֶל־",
          "noTeamim": "אֶל־",
          "plain": "אל",
          "morph": "אֶל־",
          "translit": "el",
          "start": 89.937,
          "end": 91.136,
          "phraseBreak": null
        },
        {
          "text": "שְׂדֵ֞ה",
          "noTeamim": "שְׂדֵה",
          "plain": "שדה",
          "morph": "שְׂדֵ֞ה",
          "translit": "sede",
          "start": 91.136,
          "end": 92.624,
          "phraseBreak": null
        },
        {
          "text": "עֶפְרֹ֤ן",
          "noTeamim": "עֶפְרֹן",
          "plain": "עפרן",
          "morph": "עֶפְרֹ֤ן",
          "translit": "efron",
          "start": 92.624,
          "end": 93.533,
          "phraseBreak": null
        },
        {
          "text": "בֶּן־",
          "noTeamim": "בֶּן־",
          "plain": "בן",
          "morph": "בֶּן־",
          "translit": "ben",
          "start": 93.533,
          "end": 94.091,
          "phraseBreak": null
        },
        {
          "text": "צֹ֙חַר֙",
          "noTeamim": "צֹחַר",
          "plain": "צחר",
          "morph": "צֹ֙חַר֙",
          "translit": "tzochar",
          "start": 94.091,
          "end": 94.67,
          "phraseBreak": null
        },
        {
          "text": "הַֽחִתִּ֔י",
          "noTeamim": "הַחִתִּי",
          "plain": "החתי",
          "morph": "הַֽ/חִתִּ֔י",
          "translit": "hachitiy",
          "start": 94.67,
          "end": 95.744,
          "phraseBreak": "zaqef"
        },
        {
          "text": "אֲשֶׁ֖ר",
          "noTeamim": "אֲשֶׁר",
          "plain": "אשר",
          "morph": "אֲשֶׁ֖ר",
          "translit": "asher",
          "start": 95.744,
          "end": 96.571,
          "phraseBreak": null
        },
        {
          "text": "עַל־",
          "noTeamim": "עַל־",
          "plain": "על",
          "morph": "עַל־",
          "translit": "al",
          "start": 96.571,
          "end": 97.088,
          "phraseBreak": null
        },
        {
          "text": "פְּנֵ֥י",
          "noTeamim": "פְּנֵי",
          "plain": "פני",
          "morph": "פְּנֵ֥י",
          "translit": "peneiy",
          "start": 97.088,
          "end": 97.625,
          "phraseBreak": null
        },
        {
          "text": "מַמְרֵֽא׃",
          "noTeamim": "מַמְרֵא׃",
          "plain": "ממרא",
          "morph": "מַמְרֵֽא׃",
          "translit": "mamre",
          "start": 97.625,
          "end": 98.183,
          "phraseBreak": "sof-pasuq"
        }
      ]
    },
    {
      "ref": "25:10",
      "words": [
        {
          "text": "הַשָּׂדֶ֛ה",
          "noTeamim": "הַשָּׂדֶה",
          "plain": "השדה",
          "morph": "הַ/שָּׂדֶ֛ה",
          "translit": "hasade",
          "start": 98.183,
          "end": 100.394,
          "phraseBreak": null
        },
        {
          "text": "אֲשֶׁר־",
          "noTeamim": "אֲשֶׁר־",
          "plain": "אשר",
          "morph": "אֲשֶׁר־",
          "translit": "asher",
          "start": 100.394,
          "end": 100.787,
          "phraseBreak": null
        },
        {
          "text": "קָנָ֥ה",
          "noTeamim": "קָנָה",
          "plain": "קנה",
          "morph": "קָנָ֥ה",
          "translit": "kana",
          "start": 100.787,
          "end": 101.324,
          "phraseBreak": null
        },
        {
          "text": "אַבְרָהָ֖ם",
          "noTeamim": "אַבְרָהָם",
          "plain": "אברהם",
          "morph": "אַבְרָהָ֖ם",
          "translit": "avraham",
          "start": 101.324,
          "end": 101.944,
          "phraseBreak": null
        },
        {
          "text": "מֵאֵ֣ת",
          "noTeamim": "מֵאֵת",
          "plain": "מאת",
          "morph": "מֵ/אֵ֣ת",
          "translit": "meet",
          "start": 101.944,
          "end": 102.543,
          "phraseBreak": null
        },
        {
          "text": "בְּנֵי־",
          "noTeamim": "בְּנֵי־",
          "plain": "בני",
          "morph": "בְּנֵי־",
          "translit": "beneiy",
          "start": 102.543,
          "end": 103.019,
          "phraseBreak": null
        },
        {
          "text": "חֵ֑ת",
          "noTeamim": "חֵת",
          "plain": "חת",
          "morph": "חֵ֑ת",
          "translit": "chet",
          "start": 103.019,
          "end": 103.494,
          "phraseBreak": "etnahta"
        },
        {
          "text": "שָׁ֛מָּה",
          "noTeamim": "שָׁמָּה",
          "plain": "שמה",
          "morph": "שָׁ֛מָּ/ה",
          "translit": "shama",
          "start": 103.494,
          "end": 105.581,
          "phraseBreak": null
        },
        {
          "text": "קֻבַּ֥ר",
          "noTeamim": "קֻבַּר",
          "plain": "קבר",
          "morph": "קֻבַּ֥ר",
          "translit": "kubar",
          "start": 105.581,
          "end": 106.346,
          "phraseBreak": null
        },
        {
          "text": "אַבְרָהָ֖ם",
          "noTeamim": "אַבְרָהָם",
          "plain": "אברהם",
          "morph": "אַבְרָהָ֖ם",
          "translit": "avraham",
          "start": 106.346,
          "end": 107.049,
          "phraseBreak": null
        },
        {
          "text": "וְשָׂרָ֥ה",
          "noTeamim": "וְשָׂרָה",
          "plain": "ושרה",
          "morph": "וְ/שָׂרָ֥ה",
          "translit": "vesara",
          "start": 107.049,
          "end": 107.483,
          "phraseBreak": null
        },
        {
          "text": "אִשְׁתּֽוֹ׃",
          "noTeamim": "אִשְׁתּוֹ׃",
          "plain": "אשתו",
          "morph": "אִשְׁתּֽ/וֹ׃",
          "translit": "ishto",
          "start": 107.483,
          "end": 108.268,
          "phraseBreak": "sof-pasuq"
        }
      ]
    },
    {
      "ref": "25:11",
      "words": [
        {
          "text": "וַיְהִ֗י",
          "noTeamim": "וַיְהִי",
          "plain": "ויהי",
          "morph": "וַ/יְהִ֗י",
          "translit": "vayhiy",
          "start": 108.268,
          "end": 111.182,
          "phraseBreak": null
        },
        {
          "text": "אַחֲרֵי֙",
          "noTeamim": "אַחֲרֵי",
          "plain": "אחרי",
          "morph": "אַחֲרֵי֙",
          "translit": "achareiy",
          "start": 111.182,
          "end": 112.277,
          "phraseBreak": null
        },
        {
          "text": "מ֣וֹת",
          "noTeamim": "מוֹת",
          "plain": "מות",
          "morph": "מ֣וֹת",
          "translit": "mot",
          "start": 112.277,
          "end": 112.897,
          "phraseBreak": null
        },
        {
          "text": "אַבְרָהָ֔ם",
          "noTeamim": "אַבְרָהָם",
          "plain": "אברהם",
          "morph": "אַבְרָהָ֔ם",
          "translit": "avraham",
          "start": 112.897,
          "end": 113.724,
          "phraseBreak": "zaqef"
        },
        {
          "text": "וַיְבָ֥רֶךְ",
          "noTeamim": "וַיְבָרֶךְ",
          "plain": "ויברך",
          "morph": "וַ/יְבָ֥רֶךְ",
          "translit": "vayvarech",
          "start": 113.724,
          "end": 114.571,
          "phraseBreak": null
        },
        {
          "text": "אֱלֹהִ֖ים",
          "noTeamim": "אֱלֹהִים",
          "plain": "אלהים",
          "morph": "אֱלֹהִ֖ים",
          "translit": "elohiym",
          "start": 114.571,
          "end": 115.046,
          "phraseBreak": null
        },
        {
          "text": "אֶת־",
          "noTeamim": "אֶת־",
          "plain": "את",
          "morph": "אֶת־",
          "translit": "et",
          "start": 115.046,
          "end": 115.315,
          "phraseBreak": null
        },
        {
          "text": "יִצְחָ֣ק",
          "noTeamim": "יִצְחָק",
          "plain": "יצחק",
          "morph": "יִצְחָ֣ק",
          "translit": "yitzchak",
          "start": 115.315,
          "end": 115.749,
          "phraseBreak": null
        },
        {
          "text": "בְּנ֑וֹ",
          "noTeamim": "בְּנוֹ",
          "plain": "בנו",
          "morph": "בְּנ֑/וֹ",
          "translit": "beno",
          "start": 115.749,
          "end": 116.369,
          "phraseBreak": "etnahta"
        },
        {
          "text": "וַיֵּ֣שֶׁב",
          "noTeamim": "וַיֵּשֶׁב",
          "plain": "וישב",
          "morph": "וַ/יֵּ֣שֶׁב",
          "translit": "vayeshev",
          "start": 116.369,
          "end": 117.671,
          "phraseBreak": null
        },
        {
          "text": "יִצְחָ֔ק",
          "noTeamim": "יִצְחָק",
          "plain": "יצחק",
          "morph": "יִצְחָ֔ק",
          "translit": "yitzchak",
          "start": 117.671,
          "end": 118.27,
          "phraseBreak": "zaqef"
        },
        {
          "text": "עִם־",
          "noTeamim": "עִם־",
          "plain": "עם",
          "morph": "עִם־",
          "translit": "im",
          "start": 118.27,
          "end": 118.911,
          "phraseBreak": null
        },
        {
          "text": "בְּאֵ֥ר",
          "noTeamim": "בְּאֵר",
          "plain": "באר",
          "morph": "בְּאֵ֥ר",
          "translit": "beer",
          "start": 118.911,
          "end": 119.551,
          "phraseBreak": null
        },
        {
          "text": "לַחַ֖י",
          "noTeamim": "לַחַי",
          "plain": "לחי",
          "morph": "לַחַ֖י",
          "translit": "lachay",
          "start": 119.551,
          "end": 120.213,
          "phraseBreak": null
        },
        {
          "text": "רֹאִֽי׃",
          "noTeamim": "רֹאִי׃",
          "plain": "ראי",
          "morph": "רֹאִֽי׃",
          "translit": "roiy",
          "start": 120.213,
          "end": 123.69,
          "phraseBreak": "sof-pasuq"
        }
      ]
    }
  ]
}