{
  "parasha": "Vezot Haberakhah",
  "parashaHebrew": "וְזֹאת הַבְּרָכָה",
  "cycle": "annual",
  "date": "",
  "dateHebrew": "",
  "aliyot": [
    {
      "num": 1,
      "label": "Aliya 1 — Deut 33:1–7",
      "href": "/parasha/vezot-haberakhah/aliya1.json",
      "audio": "/parasha/vezot-haberakhah/audio/aliya1.mp3",
      "duration": 108.147,
      "verseCount": 7,
      "wordCount": 79
    },
    {
      "num": 2,
      "label": "Aliya 2 — Deut 33:8–12",
      "href": "/parasha/vezot-haberakhah/aliya2.json",
      "audio": "/parasha/vezot-haberakhah/audio/aliya2.mp3",
      "duration": 83.696,
      "verseCount": 5,
      "wordCount": 68
    },
    {
      "num": 3,
      "label": "Aliya 3 — Deut 33:13–17",
      "href": "/parasha/vezot-haberakhah/aliya3.json",
      "audio": "/parasha/vezot-haberakhah/audio/aliya3.mp3",
      "duration": 74.788,
      "verseCount": 5,
      "wordCount": 54
    },
    {
      "num": 4,
      "label": "Aliya 4 — Deut 33:18–21",
      "href": "/parasha/vezot-haberakhah/aliya4.json",
      "audio": "/parasha/vezot-haberakhah/audio/aliya4.mp3",
      "duration": 59.585,
      "verseCount": 4,
      "wordCount": 49
    },
    {
      "num": 5,
      "label": "Aliya 5 — Deut 33:22–26",
      "href": "/parasha/vezot-haberakhah/aliya5.json",
      "audio": "/parasha/vezot-haberakhah/audio/aliya5.mp3",
      "duration": 57.757,
      "verseCount": 5,
      "wordCount": 43
    },
    {
      "num": 6,
      "label": "Aliya 6 — Deut 33:27–29",
      "href": "/parasha/vezot-haberakhah/aliya6.json",
      "audio": "/parasha/vezot-haberakhah/audio/aliya6.mp3",
      "duration": 60.082,
      "verseCount": 3,
      "wordCount": 44
    },
    {
      "num": 7,
      "label": "Aliya 7 — Deut 34:1–12",
      "href": "/parasha/vezot-haberakhah/aliya7.json",
      "audio": "/parasha/vezot-haberakhah/audio/aliya7.mp3",
      "duration": 248.921,
      "verseCount": 12,
      "wordCount": 176
    }
  ]
}